[
    {
        "id": "1",
        "nom": "Pizza",
        "description": "Pizza",
        "prix": "25.00 \u20ac",
        "categorie": "Plat"
    },
    {
        "id": "2",
        "nom": "Taboulet",
        "description": "Taboulet avec de la viande",
        "prix": "7.27 \u20ac",
        "categorie": "Plat"
    },
    {
        "id": "3",
        "nom": "Gateau",
        "description": "Gateau au chocolat",
        "prix": "18.00 \u20ac",
        "categorie": "Dessert"
    },
    {
        "id": "4",
        "nom": "Sushi",
        "description": "Sushi avec de la sauce samourai",
        "prix": "18.50 \u20ac",
        "categorie": "Plat"
    },
    {
        "id": "5",
        "nom": "Burger McDonald",
        "description": "Viande, Sauce Ketchup, Salade",
        "prix": "9.50 \u20ac",
        "categorie": "Plat"
    },
    {
        "id": "6",
        "nom": "Tacos mexicains",
        "description": "Tacos avec de la bonne viande",
        "prix": "15.00 \u20ac",
        "categorie": "Plat"
    },
    {
        "id": "8",
        "nom": "Lasagne",
        "description": "Lasagne avec fromages et viandes",
        "prix": "17.75 \u20ac",
        "categorie": "Entrer"
    },
    {
        "id": "9",
        "nom": "Pizza Margherita",
        "description": "Pizza Margherita",
        "prix": "10.00 \u20ac",
        "categorie": "Plat"
    }
]